LICENSE-MIT
MANIFEST.in
README.md
setup.cfg
setup.py
sdata_examples/__init__.py
sdata_examples.egg-info/PKG-INFO
sdata_examples.egg-info/SOURCES.txt
sdata_examples.egg-info/dependency_links.txt
sdata_examples.egg-info/requires.txt
sdata_examples.egg-info/top_level.txt