Metadata-Version: 2.1
Name: sdata-examples
Version: 0.1.0
Summary: structured data examples
Home-page: https://github.com/lepy/sdata_examples
Author: Lepy
Author-email: lepy@mailbox.org
Maintainer: Lepy
Maintainer-email: lepy@mailbox.org
License: MIT/Apache-2.0
Keywords: open data
Platform: UNKNOWN
Classifier: Development Status :: 3 - Alpha
Classifier: Intended Audience :: Developers
Classifier: License :: OSI Approved :: MIT License
Classifier: Natural Language :: English
Classifier: Operating System :: OS Independent
Classifier: Programming Language :: Python :: 3.6
Classifier: Programming Language :: Python :: 3.7
Classifier: Programming Language :: Python :: Implementation :: CPython
Classifier: Programming Language :: Python :: Implementation :: PyPy
